VERSION
dungeonsheets/__init__.py
dungeonsheets/armor.py
dungeonsheets/background.py
dungeonsheets/character.py
dungeonsheets/content.py
dungeonsheets/content_registry.py
dungeonsheets/create_character.py
dungeonsheets/dice.py
dungeonsheets/encounter.py
dungeonsheets/entity.py
dungeonsheets/epub.py
dungeonsheets/equipment_reader.py
dungeonsheets/exceptions.py
dungeonsheets/fill_pdf_template.py
dungeonsheets/forms.py
dungeonsheets/homebrew.py
dungeonsheets/infusions.py
dungeonsheets/latex.py
dungeonsheets/magic_items.py
dungeonsheets/make_sheets.py
dungeonsheets/mechanics.py
dungeonsheets/race.py
dungeonsheets/random_tables.py
dungeonsheets/readers.py
dungeonsheets/stats.py
dungeonsheets/weapons.py
dungeonsheets/classes/__init__.py
dungeonsheets/classes/artificer.py
dungeonsheets/classes/barbarian.py
dungeonsheets/classes/bard.py
dungeonsheets/classes/bloodhunter.py
dungeonsheets/classes/classes.py
dungeonsheets/classes/cleric.py
dungeonsheets/classes/druid.py
dungeonsheets/classes/fighter.py
dungeonsheets/classes/monk.py
dungeonsheets/classes/paladin.py
dungeonsheets/classes/ranger.py
dungeonsheets/classes/rogue.py
dungeonsheets/classes/sorceror.py
dungeonsheets/classes/warlock.py
dungeonsheets/classes/wizard.py
dungeonsheets/features/__init__.py
dungeonsheets/features/artificer.py
dungeonsheets/features/backgrounds.py
dungeonsheets/features/barbarian.py
dungeonsheets/features/bard.py
dungeonsheets/features/bloodhunter.py
dungeonsheets/features/cleric.py
dungeonsheets/features/druid.py
dungeonsheets/features/feats.py
dungeonsheets/features/features.py
dungeonsheets/features/fighter.py
dungeonsheets/features/monk.py
dungeonsheets/features/paladin.py
dungeonsheets/features/races.py
dungeonsheets/features/ranger.py
dungeonsheets/features/rogue.py
dungeonsheets/features/sorceror.py
dungeonsheets/features/warlock.py
dungeonsheets/features/wizard.py
dungeonsheets/forms/MSavage_template.tex
dungeonsheets/forms/blank-character-sheet-default.pdf
dungeonsheets-0.19.0.dist-info/LICENSE
dungeonsheets-0.19.0.dist-info/METADATA
dungeonsheets-0.19.0.dist-info/WHEEL
dungeonsheets-0.19.0.dist-info/entry_points.txt
dungeonsheets-0.19.0.dist-info/top_level.txt
dungeonsheets-0.19.0.dist-info/RECORD
