Metadata-Version: 2.1
Name: dungeonsheets
Version: 0.19.0
Summary: Dungeons and Dragons 5e Character Tools
Home-page: https://github.com/canismarko/dungeon-sheets
Download-URL: https://github.com/canismarko/dungeon-sheets/archive/master.zip
Author: Mark Wolfman
Author-email: canismarko@gmail.com
License: GPLv3
Keywords: D&D character sheets
Classifier: Development Status :: 3 - Alpha
Classifier: Environment :: Console
Classifier: License :: OSI Approved :: GNU General Public License v3 or later (GPLv3+)
Classifier: Natural Language :: English
Classifier: Programming Language :: Python :: 3.7
Classifier: Programming Language :: Python :: 3.8
Classifier: Programming Language :: Python :: 3.9
Classifier: Programming Language :: Python :: 3.10
Classifier: Programming Language :: Python :: 3.11
Classifier: Topic :: Games/Entertainment :: Role-Playing
Requires-Python: >=3.7
License-File: LICENSE
Requires-Dist: fdfgen
Requires-Dist: npyscreen
Requires-Dist: jinja2
Requires-Dist: pdfrw
Requires-Dist: sphinx
Requires-Dist: EbookLib
Requires-Dist: reportlab
